{"nodes": [{"id": "common_file_store_obs_test_go", "label": "obs_test.go", "file_type": "code", "source_file": "common/file_store/obs_test.go", "source_location": "L1"}, {"id": "obs_test_testobsupload", "label": "TestOBSUpload()", "file_type": "code", "source_file": "common/file_store/obs_test.go", "source_location": "L7"}], "edges": [{"source": "common_file_store_obs_test_go", "target": "testing", "relation": "imports_from", "confidence": "EXTRACTED", "source_file": "common/file_store/obs_test.go", "source_location": "L4", "weight": 1.0}, {"source": "common_file_store_obs_test_go", "target": "obs_test_testobsupload", "relation": "contains", "confidence": "EXTRACTED", "source_file": "common/file_store/obs_test.go", "source_location": "L7", "weight": 1.0}], "raw_calls": [{"caller_nid": "obs_test_testobsupload", "callee": "Setup", "source_file": "common/file_store/obs_test.go", "source_location": "L9"}, {"caller_nid": "obs_test_testobsupload", "callee": "UpLoad", "source_file": "common/file_store/obs_test.go", "source_location": "L10"}, {"caller_nid": "obs_test_testobsupload", "callee": "Error", "source_file": "common/file_store/obs_test.go", "source_location": "L12"}, {"caller_nid": "obs_test_testobsupload", "callee": "Log", "source_file": "common/file_store/obs_test.go", "source_location": "L14"}]}